xy_stdio_request_base/Base.py
xy_stdio_request_base/ModuleData.py
xy_stdio_request_base/Resource.py
xy_stdio_request_base/Task.py
xy_stdio_request_base/__init__.py
xy_stdio_request_base/utils.py
xy_stdio_request_base/execute/Main.py
xy_stdio_request_base/execute/__init__.py
xy_stdio_request_base-1.0.2.dist-info/LICENSE
xy_stdio_request_base-1.0.2.dist-info/METADATA
xy_stdio_request_base-1.0.2.dist-info/WHEEL
xy_stdio_request_base-1.0.2.dist-info/top_level.txt
xy_stdio_request_base-1.0.2.dist-info/RECORD
