Metadata-Version: 2.1
Name: xy_stdio_request_base
Version: 1.0.2
Summary: xy_stdio_request_base 模块
Author-email: yuyangit <yuyangit.0515@qq.com>
Classifier: Programming Language :: Python :: 3
Requires-Python: >=3.11.3
License-File: LICENSE
Requires-Dist: xy-list
